{
   "total_num_params": 12,
   "graph": {
      "node": [
         {
            "name": "x",
            "op_type": null,
            "op": "placeholder",
            "output": [
               "conv"
            ],
            "input": [],
            "attributes": {},
            "num_params": null
         },
         {
            "name": "conv",
            "op_type": "Conv2d",
            "op": "call_module",
            "output": [
               "output"
            ],
            "input": [
               "x"
            ],
            "attributes": {
               "weight": [
                  3,
                  3,
                  1,
                  1
               ],
               "bias": [
                  3
               ]
            },
            "num_params": 12
         },
         {
            "name": "output",
            "op_type": null,
            "op": "output",
            "output": [],
            "input": [
               "conv"
            ],
            "attributes": {},
            "num_params": null
         }
      ]
   }
}